async_batcher/__init__.py
async_batcher/aws/__init__.py
async_batcher/aws/dynamodb/__init__.py
async_batcher/aws/dynamodb/get.py
async_batcher/aws/dynamodb/write.py
async_batcher/batcher.py
async_batcher/exceptions.py
async_batcher/ml/__init__.py
async_batcher/ml/keras/__init__.py
async_batcher/ml/keras/model.py
async_batcher/ml/sklearn/__init__.py
async_batcher/ml/sklearn/model.py
async_batcher/scylladb/__init__.py
async_batcher/scylladb/update.py
async_batcher/sqlalchemy/__init__.py
async_batcher/sqlalchemy/write.py
async_batcher-0.2.2.dist-info/LICENSE
async_batcher-0.2.2.dist-info/METADATA
async_batcher-0.2.2.dist-info/WHEEL
async_batcher-0.2.2.dist-info/RECORD
