Metadata-Version: 2.3
Name: async-batcher
Version: 0.2.2
Summary: A service to batch your http requests.
License: Apache-2.0
Keywords: python,asyncio,rest,grpc,fastapi
Author: Hussein Awala
Author-email: hussein@awala.fr
Requires-Python: >=3.10,<4.0
Classifier: License :: OSI Approved :: Apache Software License
Classifier: Programming Language :: Python :: 3
Classifier: Programming Language :: Python :: 3.10
Classifier: Programming Language :: Python :: 3.11
Classifier: Programming Language :: Python :: 3.12
Classifier: Programming Language :: Python :: 3.13
Provides-Extra: aws
Provides-Extra: keras
Provides-Extra: scylla
Provides-Extra: sklearn
Provides-Extra: sqlalchemy
Requires-Dist: aioboto3 (>=13.1,<14.0) ; extra == "aws"
Requires-Dist: keras (>=2.12,<3.0) ; (python_version < "3.12") and (extra == "keras")
Requires-Dist: keras (>=2.12,<4) ; (python_version == "3.12") and (extra == "keras")
Requires-Dist: scikit-learn (>=1.2,<2.0) ; (python_version < "3.12") and (extra == "sklearn")
Requires-Dist: scikit-learn (>=1.3,<2.0) ; (python_version == "3.12") and (extra == "sklearn")
Requires-Dist: scylla-driver (>=3,<4) ; extra == "scylla"
Requires-Dist: sqlalchemy[asyncio] (>=1.4,<3) ; extra == "sqlalchemy"
Project-URL: Bug Tracker, https://github.com/hussein-awala/async-batcher/issues
Project-URL: Documentation, https://github.com/hussein-awala/async-batcher/blob/main/README.md
Project-URL: Repository, https://github.com/hussein-awala/async-batcher
